nice_prompts/__init__.py
nice_prompts/main.py
nice_prompts-0.4.3.dist-info/LICENSE
nice_prompts-0.4.3.dist-info/METADATA
nice_prompts-0.4.3.dist-info/WHEEL
nice_prompts-0.4.3.dist-info/top_level.txt
nice_prompts-0.4.3.dist-info/RECORD
