Metadata-Version: 2.1
Name: nice-prompts
Version: 0.4.3
Summary: Use nice prompts in your terminal e.g. multiple choice
Home-page: https://github.com/kuroyuki-simp/nice-prompts
Author: kuroyuki-simp
Author-email: insanewaifu@protonmail.com
Project-URL: Bug Tracker, https://github.com/kuroyuki-simp/nice-prompts
Project-URL: Docs, https://nice-prompts.readthedocs.io
Classifier: Programming Language :: Python :: 3
Classifier: License :: OSI Approved :: GNU Lesser General Public License v3 (LGPLv3)
Classifier: Operating System :: OS Independent
Requires-Python: >=3.6
License-File: LICENSE
Requires-Dist: blessed
